shapeguard/__init__.py
shapeguard/shapeguard.py
test/__init__.py
test/test_shapeguard.py
torch_shapeguard-1.0.3.dist-info/LICENSE
torch_shapeguard-1.0.3.dist-info/METADATA
torch_shapeguard-1.0.3.dist-info/WHEEL
torch_shapeguard-1.0.3.dist-info/top_level.txt
torch_shapeguard-1.0.3.dist-info/RECORD
