Metadata-Version: 2.1
Name: torch-shapeguard
Version: 1.0.3
Summary: ShapeGuard allows you to very succinctly assert the expected shapes of tensors in a dynamic, einsum inspired way.
Home-page: https://github.com/rasmusbergpalm/shapeguard
Author: Rasmus Berg Palm
Author-email: rasmusbergpalm@gmail.com
License: UNKNOWN
Platform: UNKNOWN
Classifier: Programming Language :: Python :: 3
Classifier: License :: OSI Approved :: MIT License
Classifier: Operating System :: OS Independent
